{
  "specId": "nethermind",
  "version": "1.0.0",
  "displayName": "Nethermind",
  "execution": {
    "executionTypes": ["docker"],
    "defaultExecutionType": "docker",
    "input": {
      "defaultConfig": {
        "http": "Enabled",
        "syncMode": "snap",
        "webSocketsPort": "8546"
      },
      "docker": {
        "raw": "",
        "containerVolumePath": "/nethermind/data",
        "forcedRawNodeInput": "--datadir /nethermind/data --JsonRpc.Host 0.0.0.0 --JsonRpc.EngineHost 0.0.0.0 --JsonRpc.EnginePort 8551 --JsonRpc.JwtSecretFile=/nethermind/data/jwtsecret"
      }
    },
    "architectures": {
      "docker": ["amd64", "arm64"],
      "binary": ["amd64", "arm64"]
    },
    "imageName": "docker.io/nethermind/nethermind",
    "binaryDownload": {
      "type": "githubReleases",
      "latestVersionUrl": "https://api.github.com/repos/NethermindEth/nethermind/releases/latest",
      "responseFormat": "githubReleases"
    },
    "execPath": "Nethermind.Runner.exe"
  },
  "category": "L1/ExecutionClient",
  "rpcTranslation": "eth-l1",
  "systemRequirements": {
    "documentationUrl": "https://docs.nethermind.io/nethermind/guides-and-helpers/validator-setup/eth2-validator#hardware-and-network-requirements",
    "cpu": {
      "cores": 4,
      "minSpeedGHz": 2.4
    },
    "memory": {
      "minSizeGBs": 16
    },
    "storage": {
      "minSizeGBs": 900,
      "ssdRequired": true
    },
    "internet": {
      "minDownloadSpeedMbps": 10,
      "minUploadSpeedMbps": 10
    },
    "docker": {
      "required": true
    }
  },
  "configTranslation": {
    "dataDir": {
      "displayName": "Node data is stored in this folder",
      "category": "Storage",
      "cliConfigPrefix": "--datadir ",
      "uiControl": {
        "type": "filePath"
      }
    },
    "http": {
      "displayName": "rpc http connections (*NiceNode requires http connections)",
      "category": "RPC APIs",
      "cliConfigPrefix": "--JsonRpc.Enabled ",
      "uiControl": {
        "type": "select/single",
        "controlTranslations": [
          {
            "value": "Enabled",
            "config": "true"
          },
          {
            "value": "Disabled"
          }
        ]
      },
      "defaultValue": "Disabled",
      "documentation": "https://docs.nethermind.io/nethermind/ethereum-client/json-rpc"
    },
    "p2pPorts": {
      "displayName": "P2P listening port (UDP and TCP)",
      "cliConfigPrefix": "--Network.P2PPort ",
      "secondaryCliConfigPrefix": "--Network.DiscoveryPort ",
      "uiControl": {
        "type": "text"
      },
      "infoDescription": "Example value: 30303",
      "defaultValue": "30303",
      "documentation": "https://docs.nethermind.io/nethermind/ethereum-client/configuration/network"
    },
    "enginePort": {
      "displayName": "Port for Execution Engine calls. Ensure the firewall is configured when enabling JSON RPC.",
      "cliConfigPrefix": "--JsonRpc.EnginePort ",
      "defaultValue": "8551",
      "uiControl": {
        "type": "text"
      },
      "documentation": "https://docs.nethermind.io/nethermind/ethereum-client/configuration/jsonrpc"
    },
    "httpPort": {
      "displayName": "HTTP-RPC server listening port",
      "cliConfigPrefix": "--JsonRpc.Port ",
      "defaultValue": "8545",
      "uiControl": {
        "type": "text"
      },
      "documentation": "https://docs.nethermind.io/nethermind/ethereum-client/json-rpc"
    },
    "httpApis": {
      "displayName": "Enabled HTTP APIs",
      "category": "RPC APIs",
      "cliConfigPrefix": "--JsonRpc.EnabledModules ",
      "valuesJoinStr": ",",
      "uiControl": {
        "type": "select/multiple",
        "controlTranslations": [
          {
            "value": "Eth",
            "config": "Eth"
          },
          {
            "value": "Subscribe",
            "config": "Subscribe"
          },
          {
            "value": "Trace",
            "config": "Trace"
          },
          {
            "value": "TxPool",
            "config": "TxPool"
          },
          {
            "value": "Web3",
            "config": "Web3"
          },

          {
            "value": "Personal",
            "config": "Personal"
          },
          {
            "value": "Proof",
            "config": "Proof"
          },
          {
            "value": "Net",
            "config": "Net"
          },
          {
            "value": "Parity",
            "config": "Parity"
          },
          {
            "value": "Health",
            "config": "Health"
          }
        ]
      },
      "defaultValue": [
        "Eth",
        "Subscribe",
        "Trace",
        "TxPool",
        "Web3",
        "Personal",
        "Proof",
        "Net",
        "Parity",
        "Health"
      ],
      "documentation": "https://docs.nethermind.io/nethermind/ethereum-client/json-rpc"
    },
    "syncMode": {
      "displayName": "Node synchronization mode",
      "category": "Syncronization",
      "uiControl": {
        "type": "select/single",
        "controlTranslations": [
          {
            "value": "fast",
            "config": "--Sync.FastSync true"
          },
          {
            "value": "snap",
            "config": "--Sync.SnapSync true"
          }
        ]
      },
      "defaultValue": "fast",
      "documentation": "https://docs.nethermind.io/nethermind/ethereum-client/sync-modes"
    },
    "webSocketsPort": {
      "displayName": "Port number for JSON RPC web sockets calls",
      "cliConfigPrefix": "--JsonRpc.WebSocketsPort ",
      "defaultValue": "8545",
      "niceNodeDefaultValue": "8545",
      "uiControl": {
        "type": "text"
      },
      "documentation": "https://docs.nethermind.io/nethermind/ethereum-client/configuration/jsonrpc",
      "infoDescription": "Port number for JSON RPC web sockets calls. By default same port is used as regular HTTP JSON RPC. Ensure the firewall is configured when enabling JSON RPC."
    },
    "maxPeerCount": {
      "displayName": "Max Peer Count (set to low number to use less bandwidth)",
      "cliConfigPrefix": "--Network.ActivePeersMaxCount ",
      "defaultValue": "50",
      "uiControl": {
        "type": "text"
      },
      "documentation": "https://docs.nethermind.io/nethermind/ethereum-client/configuration/network"
    }
  },
  "documentation": {
    "default": "https://docs.nethermind.io/nethermind/",
    "docker": "https://docs.nethermind.io/nethermind/ethereum-client/docker"
  },
  "iconUrl": "https://clientdiversity.org/assets/img/execution-clients/nethermind-logo.png"
}
